pyprecip/__init__.py
pyprecip/main.py
pyprecip-0.1.0.dist-info/LICENSE
pyprecip-0.1.0.dist-info/METADATA
pyprecip-0.1.0.dist-info/WHEEL
pyprecip-0.1.0.dist-info/top_level.txt
pyprecip-0.1.0.dist-info/RECORD
